hindsight/__init__.py
hindsight/common.py
hindsight/hindsight.py
hindsight/restore.py
hindsight/save.py
hindsight/test.py
hindsight_ubuntu-0.0.3.dist-info/LICENSE.md
hindsight_ubuntu-0.0.3.dist-info/METADATA
hindsight_ubuntu-0.0.3.dist-info/WHEEL
hindsight_ubuntu-0.0.3.dist-info/entry_points.txt
hindsight_ubuntu-0.0.3.dist-info/top_level.txt
hindsight_ubuntu-0.0.3.dist-info/RECORD
