Metadata-Version: 2.1
Name: hindsight-ubuntu
Version: 0.0.3
Summary: Remember the position, size and virtual desktop of your open windows and restore them at a later point.
Home-page: https://github.com/TroyWilliams3687/hindsight
Author: Troy Williams
Author-email: troy.williams@bluebill.net
License: MIT
Platform: UNKNOWN
Classifier: License :: OSI Approved :: MIT License
Classifier: Programming Language :: Python :: 3
Classifier: Programming Language :: Python :: 3.9
Classifier: Operating System :: POSIX :: Linux
Classifier: Topic :: Desktop Environment :: Gnome
Requires-Python: >=3.9
License-File: LICENSE.md
Requires-Dist: click
Requires-Dist: appdirs
Requires-Dist: pyyaml
